odoo/addons/hr_holidays_public_city/README.rst
odoo/addons/hr_holidays_public_city/__init__.py
odoo/addons/hr_holidays_public_city/__manifest__.py
odoo/addons/hr_holidays_public_city/i18n/es.po
odoo/addons/hr_holidays_public_city/i18n/hr_holidays_public_city.pot
odoo/addons/hr_holidays_public_city/i18n/it.po
odoo/addons/hr_holidays_public_city/models/__init__.py
odoo/addons/hr_holidays_public_city/models/calendar_public_holiday_line.py
odoo/addons/hr_holidays_public_city/models/hr_leave.py
odoo/addons/hr_holidays_public_city/readme/CONTRIBUTORS.md
odoo/addons/hr_holidays_public_city/readme/DESCRIPTION.md
odoo/addons/hr_holidays_public_city/static/description/icon.png
odoo/addons/hr_holidays_public_city/static/description/index.html
odoo/addons/hr_holidays_public_city/tests/__init__.py
odoo/addons/hr_holidays_public_city/tests/test_holidays_calculation.py
odoo/addons/hr_holidays_public_city/tests/test_holidays_public.py
odoo/addons/hr_holidays_public_city/views/calendar_public_holiday_view.xml
odoo_addon_hr_holidays_public_city-18.0.1.0.0.2.dist-info/METADATA
odoo_addon_hr_holidays_public_city-18.0.1.0.0.2.dist-info/WHEEL
odoo_addon_hr_holidays_public_city-18.0.1.0.0.2.dist-info/top_level.txt
odoo_addon_hr_holidays_public_city-18.0.1.0.0.2.dist-info/RECORD
